<?xml version="1.0"?>
<!DOCTYPE hibernate-mapping PUBLIC "-//Hibernate/Hibernate Mapping DTD 3.0//EN"
"http://www.hibernate.org/dtd/hibernate-mapping-3.0.dtd">
<!-- Generated Jan 31, 2014 8:16:09 PM by Hibernate Tools 4.0.0 -->
<hibernate-mapping>
    <class name="com.posbravo.model.Authentication" table="authentication" catalog="posbravo">
        <id name="authId" type="java.lang.Integer">
            <column name="AuthID" />
            <generator class="identity" />
        </id>
        <property name="userId" type="java.lang.Integer">
            <column name="UserID" />
        </property>
        <property name="userName" type="string">
            <column name="UserName" />
        </property>
        <property name="password" type="string">
            <column name="Password" />
        </property>
        <property name="pin" type="java.lang.Integer">
            <column name="Pin" />
        </property>
        <property name="isLocked" type="java.lang.Boolean">
            <column name="IsLocked" />
        </property>
        <property name="maxPwAttempt" type="string">
            <column name="MaxPwAttempt" />
        </property>
        <property name="maxPinAttempt" type="java.lang.Integer">
            <column name="MaxPinAttempt" />
        </property>
    </class>
</hibernate-mapping>
